setup.py
tiro/__init__.py
tiro/abbreviate.py
tiro/regnets.py
tiro/rules_generator.py
tiro.egg-info/PKG-INFO
tiro.egg-info/SOURCES.txt
tiro.egg-info/dependency_links.txt
tiro.egg-info/top_level.txt