Metadata-Version: 1.0
Name: tiro
Version: 0.1
Summary: An abbreviation engine.
Home-page: http://github.com/subsetpark/tiro
Author: Zach Smith
Author-email: zd@zdsmith.com
License: UNKNOWN
Platform: UNKNOWN
